btcoreutil/__init__.py
btcoreutil/__version__.py
btcoreutil/util.py
btcoreutil-0.1.0.dist-info/licenses/LICENSE
btcoreutil-0.1.0.dist-info/METADATA
btcoreutil-0.1.0.dist-info/WHEEL
btcoreutil-0.1.0.dist-info/top_level.txt
btcoreutil-0.1.0.dist-info/RECORD
